swagroutes/__init__.py
swagroutes/__main__.py
swagroutes/cli.py
swagroutes/extractor.py
tests/__init__.py
tests/test_extractor.py
swagroutes-1.0.2.dist-info/LICENSE
swagroutes-1.0.2.dist-info/METADATA
swagroutes-1.0.2.dist-info/WHEEL
swagroutes-1.0.2.dist-info/entry_points.txt
swagroutes-1.0.2.dist-info/top_level.txt
swagroutes-1.0.2.dist-info/RECORD
