Metadata-Version: 2.1
Name: swagroutes
Version: 1.0.2
Summary: Command-line tool that extracts and lists API routes from Swagger files in YAML or JSON format.
Home-page: https://github.com/amalmurali47/swagroutes
Author: Amal Murali
Author-email: amalmurali47@gmail.com
Classifier: Programming Language :: Python :: 3
Classifier: License :: OSI Approved :: MIT License
Classifier: Operating System :: OS Independent
Requires-Python: >=3.6
License-File: LICENSE
Requires-Dist: PyYAML (>=6.0)
